[
	{"endpoint1": {"floor": 1, "x": 50, "y": 123}, "endpoint2": {"floor": 1, "x": 63, "y": 145}},
	{"endpoint1": {"floor": 1, "x": 50, "y": 123}, "endpoint2": {"floor": 1, "x": 117, "y": 78}},
	{"endpoint1": {"floor": 1, "x": 110, "y": 343}, "endpoint2": {"floor": 1, "x": 110, "y": 368}},
	{"endpoint1": {"floor": 1, "x": 110, "y": 343}, "endpoint2": {"floor": 1, "x": 321, "y": 343}},
	{"endpoint1": {"floor": 1, "x": 110, "y": 368}, "endpoint2": {"floor": 1, "x": 110, "y": 397}},
	{"endpoint1": {"floor": 1, "x": 110, "y": 397}, "endpoint2": {"floor": 1, "x": 121, "y": 397}},
	{"endpoint1": {"floor": 1, "x": 117, "y": 78}, "endpoint2": {"floor": 1, "x": 185, "y": 33}},
	{"endpoint1": {"floor": 1, "x": 117, "y": 78}, "endpoint2": {"floor": 1, "x": 199, "y": 202}},
	{"endpoint1": {"floor": 1, "x": 184, "y": 219}, "endpoint2": {"floor": 1, "x": 190, "y": 235}},
	{"endpoint1": {"floor": 1, "x": 184, "y": 219}, "endpoint2": {"floor": 1, "x": 199, "y": 202}},
	{"endpoint1": {"floor": 1, "x": 190, "y": 235}, "endpoint2": {"floor": 1, "x": 237, "y": 234}},
	{"endpoint1": {"floor": 1, "x": 199, "y": 202}, "endpoint2": {"floor": 1, "x": 246, "y": 186}},
	{"endpoint1": {"floor": 1, "x": 237, "y": 234}, "endpoint2": {"floor": 1, "x": 273, "y": 223}},
	{"endpoint1": {"floor": 1, "x": 246, "y": 186}, "endpoint2": {"floor": 1, "x": 265, "y": 196}},
	{"endpoint1": {"floor": 1, "x": 246, "y": 186}, "endpoint2": {"floor": 1, "x": 269, "y": 166}},
	{"endpoint1": {"floor": 1, "x": 265, "y": 196}, "endpoint2": {"floor": 1, "x": 273, "y": 223}},
	{"endpoint1": {"floor": 1, "x": 265, "y": 196}, "endpoint2": {"floor": 1, "x": 278, "y": 174}},
	{"endpoint1": {"floor": 1, "x": 269, "y": 166}, "endpoint2": {"floor": 1, "x": 278, "y": 174}},
	{"endpoint1": {"floor": 1, "x": 273, "y": 223}, "endpoint2": {"floor": 1, "x": 321, "y": 235}},
	{"endpoint1": {"floor": 1, "x": 293, "y": 431}, "endpoint2": {"floor": 1, "x": 293, "y": 440}},
	{"endpoint1": {"floor": 1, "x": 293, "y": 431}, "endpoint2": {"floor": 1, "x": 321, "y": 431}},
	{"endpoint1": {"floor": 1, "x": 294, "y": 254}, "endpoint2": {"floor": 1, "x": 294, "y": 272}},
	{"endpoint1": {"floor": 1, "x": 294, "y": 254}, "endpoint2": {"floor": 1, "x": 321, "y": 254}},
	{"endpoint1": {"floor": 1, "x": 321, "y": 431}, "endpoint2": {"floor": 1, "x": 321, "y": 400}},
	{"endpoint1": {"floor": 1, "x": 321, "y": 235}, "endpoint2": {"floor": 1, "x": 321, "y": 254}},
	{"endpoint1": {"floor": 1, "x": 321, "y": 235}, "endpoint2": {"floor": 1, "x": 380, "y": 250}},
	{"endpoint1": {"floor": 1, "x": 321, "y": 343}, "endpoint2": {"floor": 1, "x": 321, "y": 400}},
	{"endpoint1": {"floor": 1, "x": 321, "y": 343}, "endpoint2": {"floor": 1, "x": 321, "y": 254}},
	{"endpoint1": {"floor": 1, "x": 321, "y": 400}, "endpoint2": {"floor": 1, "x": 457, "y": 399}},
	{"endpoint1": {"floor": 1, "x": 380, "y": 250}, "endpoint2": {"floor": 1, "x": 380, "y": 171}},
	{"endpoint1": {"floor": 1, "x": 380, "y": 250}, "endpoint2": {"floor": 1, "x": 438, "y": 268}},
	{"endpoint1": {"floor": 1, "x": 403, "y": 237}, "endpoint2": {"floor": 1, "x": 438, "y": 249}},
	{"endpoint1": {"floor": 1, "x": 430, "y": 459}, "endpoint2": {"floor": 1, "x": 430, "y": 469}},
	{"endpoint1": {"floor": 1, "x": 430, "y": 459}, "endpoint2": {"floor": 1, "x": 457, "y": 459}},
	{"endpoint1": {"floor": 1, "x": 438, "y": 268}, "endpoint2": {"floor": 1, "x": 438, "y": 249}},
	{"endpoint1": {"floor": 1, "x": 438, "y": 268}, "endpoint2": {"floor": 1, "x": 458, "y": 274}},
	{"endpoint1": {"floor": 1, "x": 438, "y": 249}, "endpoint2": {"floor": 1, "x": 438, "y": 170}},
	{"endpoint1": {"floor": 1, "x": 457, "y": 459}, "endpoint2": {"floor": 1, "x": 457, "y": 427}},
	{"endpoint1": {"floor": 1, "x": 457, "y": 399}, "endpoint2": {"floor": 1, "x": 457, "y": 427}},
	{"endpoint1": {"floor": 1, "x": 457, "y": 399}, "endpoint2": {"floor": 1, "x": 458, "y": 274}},
	{"endpoint1": {"floor": 1, "x": 457, "y": 427}, "endpoint2": {"floor": 1, "x": 594, "y": 428}},
	{"endpoint1": {"floor": 1, "x": 458, "y": 274}, "endpoint2": {"floor": 1, "x": 528, "y": 293}},
	{"endpoint1": {"floor": 1, "x": 528, "y": 293}, "endpoint2": {"floor": 1, "x": 595, "y": 311}},
	{"endpoint1": {"floor": 1, "x": 594, "y": 488}, "endpoint2": {"floor": 1, "x": 594, "y": 454}},
	{"endpoint1": {"floor": 1, "x": 594, "y": 428}, "endpoint2": {"floor": 1, "x": 594, "y": 454}},
	{"endpoint1": {"floor": 1, "x": 594, "y": 428}, "endpoint2": {"floor": 1, "x": 595, "y": 311}},
	{"endpoint1": {"floor": 1, "x": 594, "y": 454}, "endpoint2": {"floor": 1, "x": 698, "y": 455}},
	{"endpoint1": {"floor": 1, "x": 595, "y": 311}, "endpoint2": {"floor": 1, "x": 613, "y": 316}},
	{"endpoint1": {"floor": 1, "x": 612, "y": 331}, "endpoint2": {"floor": 1, "x": 612, "y": 353}},
	{"endpoint1": {"floor": 1, "x": 612, "y": 353}, "endpoint2": {"floor": 1, "x": 622, "y": 353}},
	{"endpoint1": {"floor": 1, "x": 613, "y": 316}, "endpoint2": {"floor": 1, "x": 622, "y": 319}},
	{"endpoint1": {"floor": 1, "x": 622, "y": 319}, "endpoint2": {"floor": 1, "x": 622, "y": 353}},
	{"endpoint1": {"floor": 1, "x": 622, "y": 319}, "endpoint2": {"floor": 1, "x": 668, "y": 331}},
	{"endpoint1": {"floor": 1, "x": 667, "y": 288}, "endpoint2": {"floor": 1, "x": 668, "y": 331}},
	{"endpoint1": {"floor": 1, "x": 668, "y": 331}, "endpoint2": {"floor": 1, "x": 668, "y": 377}},
	{"endpoint1": {"floor": 1, "x": 668, "y": 377}, "endpoint2": {"floor": 1, "x": 704, "y": 411}},
	{"endpoint1": {"floor": 1, "x": 689, "y": 483}, "endpoint2": {"floor": 1, "x": 698, "y": 483}},
	{"endpoint1": {"floor": 1, "x": 698, "y": 483}, "endpoint2": {"floor": 1, "x": 698, "y": 455}},
	{"endpoint1": {"floor": 1, "x": 704, "y": 411}, "endpoint2": {"floor": 1, "x": 761, "y": 415}},
	{"endpoint1": {"floor": 1, "x": 761, "y": 415}, "endpoint2": {"floor": 1, "x": 782, "y": 407}},
	{"endpoint1": {"floor": 1, "x": 782, "y": 407}, "endpoint2": {"floor": 1, "x": 944, "y": 408}},
	{"endpoint1": {"floor": 1, "x": 917, "y": 382}, "endpoint2": {"floor": 1, "x": 944, "y": 382}},
	{"endpoint1": {"floor": 1, "x": 944, "y": 382}, "endpoint2": {"floor": 1, "x": 944, "y": 408}},
	{"endpoint1": {"floor": 1, "x": 944, "y": 382}, "endpoint2": {"floor": 1, "x": 944, "y": 322}},
	{"endpoint1": {"floor": 1, "x": 944, "y": 408}, "endpoint2": {"floor": 1, "x": 999, "y": 408}},
	{"endpoint1": {"floor": 1, "x": 944, "y": 322}, "endpoint2": {"floor": 1, "x": 955, "y": 322}},
	{"endpoint1": {"floor": 1, "x": 955, "y": 322}, "endpoint2": {"floor": 1, "x": 955, "y": 301}},
	{"endpoint1": {"floor": 1, "x": 955, "y": 301}, "endpoint2": {"floor": 1, "x": 1000, "y": 301}},
	{"endpoint1": {"floor": 1, "x": 999, "y": 408}, "endpoint2": {"floor": 1, "x": 1000, "y": 301}},
	{"endpoint1": {"floor": 1, "x": 999, "y": 408}, "endpoint2": {"floor": 1, "x": 1015, "y": 409}},
	{"endpoint1": {"floor": 1, "x": 1000, "y": 301}, "endpoint2": {"floor": 1, "x": 1001, "y": 285}},
	{"endpoint1": {"floor": 1, "x": 1015, "y": 318}, "endpoint2": {"floor": 1, "x": 1015, "y": 409}},
	{"endpoint1": {"floor": 1, "x": 1015, "y": 409}, "endpoint2": {"floor": 1, "x": 1077, "y": 409}},
	{"endpoint1": {"floor": 1, "x": 121, "y": 397}, "endpoint2": {"floor": 2, "x": 121, "y": 397}},
	{"endpoint1": {"floor": 1, "x": 293, "y": 440}, "endpoint2": {"floor": 2, "x": 293, "y": 439}},
	{"endpoint1": {"floor": 1, "x": 294, "y": 272}, "endpoint2": {"floor": 2, "x": 294, "y": 272}},
	{"endpoint1": {"floor": 1, "x": 403, "y": 237}, "endpoint2": {"floor": 2, "x": 403, "y": 238}},
	{"endpoint1": {"floor": 1, "x": 430, "y": 469}, "endpoint2": {"floor": 2, "x": 430, "y": 468}},
	{"endpoint1": {"floor": 1, "x": 528, "y": 293}, "endpoint2": {"floor": 2, "x": 528, "y": 293}, "name": "Elevator"},
	{"endpoint1": {"floor": 1, "x": 612, "y": 331}, "endpoint2": {"floor": 2, "x": 613, "y": 330}},
	{"endpoint1": {"floor": 1, "x": 689, "y": 483}, "endpoint2": {"floor": 2, "x": 688, "y": 482}},
	{"endpoint1": {"floor": 2, "x": 112, "y": 371}, "endpoint2": {"floor": 2, "x": 112, "y": 397}},
	{"endpoint1": {"floor": 2, "x": 112, "y": 371}, "endpoint2": {"floor": 2, "x": 121, "y": 371}},
	{"endpoint1": {"floor": 2, "x": 121, "y": 397}, "endpoint2": {"floor": 2, "x": 121, "y": 371}},
	{"endpoint1": {"floor": 2, "x": 121, "y": 371}, "endpoint2": {"floor": 2, "x": 322, "y": 371}},
	{"endpoint1": {"floor": 2, "x": 293, "y": 430}, "endpoint2": {"floor": 2, "x": 322, "y": 431}},
	{"endpoint1": {"floor": 2, "x": 293, "y": 439}, "endpoint2": {"floor": 2, "x": 322, "y": 439}},
	{"endpoint1": {"floor": 2, "x": 294, "y": 272}, "endpoint2": {"floor": 2, "x": 303, "y": 272}},
	{"endpoint1": {"floor": 2, "x": 303, "y": 246}, "endpoint2": {"floor": 2, "x": 303, "y": 272}},
	{"endpoint1": {"floor": 2, "x": 303, "y": 272}, "endpoint2": {"floor": 2, "x": 322, "y": 277}},
	{"endpoint1": {"floor": 2, "x": 322, "y": 371}, "endpoint2": {"floor": 2, "x": 322, "y": 277}},
	{"endpoint1": {"floor": 2, "x": 322, "y": 371}, "endpoint2": {"floor": 2, "x": 322, "y": 399}},
	{"endpoint1": {"floor": 2, "x": 322, "y": 250}, "endpoint2": {"floor": 2, "x": 322, "y": 277}},
	{"endpoint1": {"floor": 2, "x": 322, "y": 250}, "endpoint2": {"floor": 2, "x": 373, "y": 263}},
	{"endpoint1": {"floor": 2, "x": 322, "y": 399}, "endpoint2": {"floor": 2, "x": 322, "y": 431}},
	{"endpoint1": {"floor": 2, "x": 322, "y": 399}, "endpoint2": {"floor": 2, "x": 458, "y": 399}},
	{"endpoint1": {"floor": 2, "x": 322, "y": 431}, "endpoint2": {"floor": 2, "x": 322, "y": 439}},
	{"endpoint1": {"floor": 2, "x": 373, "y": 263}, "endpoint2": {"floor": 2, "x": 377, "y": 250}},
	{"endpoint1": {"floor": 2, "x": 373, "y": 263}, "endpoint2": {"floor": 2, "x": 459, "y": 288}},
	{"endpoint1": {"floor": 2, "x": 377, "y": 250}, "endpoint2": {"floor": 2, "x": 382, "y": 232}},
	{"endpoint1": {"floor": 2, "x": 377, "y": 250}, "endpoint2": {"floor": 2, "x": 399, "y": 256}},
	{"endpoint1": {"floor": 2, "x": 382, "y": 232}, "endpoint2": {"floor": 2, "x": 403, "y": 238}},
	{"endpoint1": {"floor": 2, "x": 430, "y": 459}, "endpoint2": {"floor": 2, "x": 458, "y": 459}},
	{"endpoint1": {"floor": 2, "x": 430, "y": 468}, "endpoint2": {"floor": 2, "x": 458, "y": 468}},
	{"endpoint1": {"floor": 2, "x": 458, "y": 459}, "endpoint2": {"floor": 2, "x": 458, "y": 468}},
	{"endpoint1": {"floor": 2, "x": 458, "y": 459}, "endpoint2": {"floor": 2, "x": 458, "y": 427}},
	{"endpoint1": {"floor": 2, "x": 458, "y": 399}, "endpoint2": {"floor": 2, "x": 458, "y": 427}},
	{"endpoint1": {"floor": 2, "x": 458, "y": 399}, "endpoint2": {"floor": 2, "x": 459, "y": 288}},
	{"endpoint1": {"floor": 2, "x": 458, "y": 427}, "endpoint2": {"floor": 2, "x": 595, "y": 427}},
	{"endpoint1": {"floor": 2, "x": 459, "y": 288}, "endpoint2": {"floor": 2, "x": 524, "y": 306}},
	{"endpoint1": {"floor": 2, "x": 524, "y": 306}, "endpoint2": {"floor": 2, "x": 528, "y": 293}},
	{"endpoint1": {"floor": 2, "x": 524, "y": 306}, "endpoint2": {"floor": 2, "x": 595, "y": 325}},
	{"endpoint1": {"floor": 2, "x": 595, "y": 427}, "endpoint2": {"floor": 2, "x": 595, "y": 325}},
	{"endpoint1": {"floor": 2, "x": 595, "y": 427}, "endpoint2": {"floor": 2, "x": 595, "y": 455}},
	{"endpoint1": {"floor": 2, "x": 595, "y": 325}, "endpoint2": {"floor": 2, "x": 613, "y": 330}},
	{"endpoint1": {"floor": 2, "x": 595, "y": 455}, "endpoint2": {"floor": 2, "x": 595, "y": 472}},
	{"endpoint1": {"floor": 2, "x": 595, "y": 455}, "endpoint2": {"floor": 2, "x": 688, "y": 455}},
	{"endpoint1": {"floor": 2, "x": 613, "y": 330}, "endpoint2": {"floor": 2, "x": 622, "y": 333}},
	{"endpoint1": {"floor": 2, "x": 622, "y": 333}, "endpoint2": {"floor": 2, "x": 622, "y": 353}},
	{"endpoint1": {"floor": 2, "x": 688, "y": 455}, "endpoint2": {"floor": 2, "x": 688, "y": 482}},
	{"endpoint1": {"floor": 2, "x": 688, "y": 455}, "endpoint2": {"floor": 2, "x": 699, "y": 455}},
	{"endpoint1": {"floor": 2, "x": 699, "y": 482}, "endpoint2": {"floor": 2, "x": 699, "y": 455}},
	{"endpoint1": {"floor": 2, "x": 112, "y": 397}, "endpoint2": {"floor": 3, "x": 112, "y": 398}},
	{"endpoint1": {"floor": 2, "x": 293, "y": 430}, "endpoint2": {"floor": 3, "x": 293, "y": 430}},
	{"endpoint1": {"floor": 2, "x": 303, "y": 246}, "endpoint2": {"floor": 3, "x": 303, "y": 247}},
	{"endpoint1": {"floor": 2, "x": 399, "y": 256}, "endpoint2": {"floor": 3, "x": 399, "y": 256}},
	{"endpoint1": {"floor": 2, "x": 430, "y": 459}, "endpoint2": {"floor": 3, "x": 431, "y": 460}},
	{"endpoint1": {"floor": 2, "x": 528, "y": 293}, "endpoint2": {"floor": 3, "x": 528, "y": 293}, "name": "Elevator"},
	{"endpoint1": {"floor": 2, "x": 622, "y": 353}, "endpoint2": {"floor": 3, "x": 622, "y": 353}},
	{"endpoint1": {"floor": 2, "x": 699, "y": 482}, "endpoint2": {"floor": 3, "x": 699, "y": 483}},
	{"endpoint1": {"floor": 3, "x": 112, "y": 398}, "endpoint2": {"floor": 3, "x": 121, "y": 398}},
	{"endpoint1": {"floor": 3, "x": 112, "y": 372}, "endpoint2": {"floor": 3, "x": 122, "y": 371}},
	{"endpoint1": {"floor": 3, "x": 121, "y": 398}, "endpoint2": {"floor": 3, "x": 122, "y": 371}},
	{"endpoint1": {"floor": 3, "x": 122, "y": 371}, "endpoint2": {"floor": 3, "x": 294, "y": 371}},
	{"endpoint1": {"floor": 3, "x": 293, "y": 430}, "endpoint2": {"floor": 3, "x": 293, "y": 441}},
	{"endpoint1": {"floor": 3, "x": 293, "y": 441}, "endpoint2": {"floor": 3, "x": 322, "y": 441}},
	{"endpoint1": {"floor": 3, "x": 294, "y": 371}, "endpoint2": {"floor": 3, "x": 294, "y": 272}},
	{"endpoint1": {"floor": 3, "x": 294, "y": 371}, "endpoint2": {"floor": 3, "x": 322, "y": 371}},
	{"endpoint1": {"floor": 3, "x": 294, "y": 244}, "endpoint2": {"floor": 3, "x": 294, "y": 272}},
	{"endpoint1": {"floor": 3, "x": 294, "y": 244}, "endpoint2": {"floor": 3, "x": 303, "y": 247}},
	{"endpoint1": {"floor": 3, "x": 294, "y": 272}, "endpoint2": {"floor": 3, "x": 351, "y": 272}},
	{"endpoint1": {"floor": 3, "x": 322, "y": 441}, "endpoint2": {"floor": 3, "x": 322, "y": 371}},
	{"endpoint1": {"floor": 3, "x": 322, "y": 371}, "endpoint2": {"floor": 3, "x": 458, "y": 371}},
	{"endpoint1": {"floor": 3, "x": 351, "y": 272}, "endpoint2": {"floor": 3, "x": 413, "y": 288}},
	{"endpoint1": {"floor": 3, "x": 399, "y": 256}, "endpoint2": {"floor": 3, "x": 420, "y": 263}},
	{"endpoint1": {"floor": 3, "x": 413, "y": 288}, "endpoint2": {"floor": 3, "x": 420, "y": 263}},
	{"endpoint1": {"floor": 3, "x": 413, "y": 288}, "endpoint2": {"floor": 3, "x": 458, "y": 300}},
	{"endpoint1": {"floor": 3, "x": 431, "y": 460}, "endpoint2": {"floor": 3, "x": 431, "y": 469}},
	{"endpoint1": {"floor": 3, "x": 431, "y": 469}, "endpoint2": {"floor": 3, "x": 458, "y": 469}},
	{"endpoint1": {"floor": 3, "x": 458, "y": 300}, "endpoint2": {"floor": 3, "x": 458, "y": 371}},
	{"endpoint1": {"floor": 3, "x": 458, "y": 300}, "endpoint2": {"floor": 3, "x": 528, "y": 319}},
	{"endpoint1": {"floor": 3, "x": 458, "y": 371}, "endpoint2": {"floor": 3, "x": 458, "y": 399}},
	{"endpoint1": {"floor": 3, "x": 458, "y": 399}, "endpoint2": {"floor": 3, "x": 458, "y": 469}},
	{"endpoint1": {"floor": 3, "x": 458, "y": 399}, "endpoint2": {"floor": 3, "x": 595, "y": 399}},
	{"endpoint1": {"floor": 3, "x": 528, "y": 319}, "endpoint2": {"floor": 3, "x": 528, "y": 293}},
	{"endpoint1": {"floor": 3, "x": 528, "y": 319}, "endpoint2": {"floor": 3, "x": 595, "y": 337}},
	{"endpoint1": {"floor": 3, "x": 595, "y": 399}, "endpoint2": {"floor": 3, "x": 595, "y": 337}},
	{"endpoint1": {"floor": 3, "x": 595, "y": 399}, "endpoint2": {"floor": 3, "x": 595, "y": 483}},
	{"endpoint1": {"floor": 3, "x": 595, "y": 337}, "endpoint2": {"floor": 3, "x": 613, "y": 330}},
	{"endpoint1": {"floor": 3, "x": 595, "y": 483}, "endpoint2": {"floor": 3, "x": 595, "y": 495}},
	{"endpoint1": {"floor": 3, "x": 595, "y": 483}, "endpoint2": {"floor": 3, "x": 699, "y": 483}},
	{"endpoint1": {"floor": 3, "x": 613, "y": 353}, "endpoint2": {"floor": 3, "x": 613, "y": 330}},
	{"endpoint1": {"floor": 3, "x": 613, "y": 353}, "endpoint2": {"floor": 3, "x": 622, "y": 353}},
	{"endpoint1": {"floor": 3, "x": 528, "y": 293}, "endpoint2": {"floor": 4, "x": 528, "y": 293}, "name": "Elevator"},
	{"endpoint1": {"floor": 4, "x": 320, "y": 385}, "endpoint2": {"floor": 4, "x": 320, "y": 283}},
	{"endpoint1": {"floor": 4, "x": 320, "y": 385}, "endpoint2": {"floor": 4, "x": 458, "y": 407}},
	{"endpoint1": {"floor": 4, "x": 320, "y": 283}, "endpoint2": {"floor": 4, "x": 363, "y": 283}},
	{"endpoint1": {"floor": 4, "x": 363, "y": 283}, "endpoint2": {"floor": 4, "x": 363, "y": 273}},
	{"endpoint1": {"floor": 4, "x": 363, "y": 273}, "endpoint2": {"floor": 4, "x": 454, "y": 299}},
	{"endpoint1": {"floor": 4, "x": 454, "y": 299}, "endpoint2": {"floor": 4, "x": 458, "y": 321}},
	{"endpoint1": {"floor": 4, "x": 454, "y": 299}, "endpoint2": {"floor": 4, "x": 478, "y": 303}},
	{"endpoint1": {"floor": 4, "x": 458, "y": 321}, "endpoint2": {"floor": 4, "x": 458, "y": 407}},
	{"endpoint1": {"floor": 4, "x": 458, "y": 321}, "endpoint2": {"floor": 4, "x": 475, "y": 324}},
	{"endpoint1": {"floor": 4, "x": 458, "y": 407}, "endpoint2": {"floor": 4, "x": 561, "y": 407}},
	{"endpoint1": {"floor": 4, "x": 475, "y": 324}, "endpoint2": {"floor": 4, "x": 485, "y": 315}},
	{"endpoint1": {"floor": 4, "x": 478, "y": 303}, "endpoint2": {"floor": 4, "x": 485, "y": 315}},
	{"endpoint1": {"floor": 4, "x": 485, "y": 315}, "endpoint2": {"floor": 4, "x": 528, "y": 320}},
	{"endpoint1": {"floor": 4, "x": 528, "y": 320}, "endpoint2": {"floor": 4, "x": 528, "y": 293}},
	{"endpoint1": {"floor": 4, "x": 528, "y": 320}, "endpoint2": {"floor": 4, "x": 554, "y": 326}}
]
